MofanPythonGitLinuxXilieJiaocheng20201031Fix1/README.md
MofanPythonGitLinuxXilieJiaocheng20201031Fix1/__init__.py
MofanPythonGitLinuxXilieJiaocheng20201031Fix1/__main__.py
MofanPythonGitLinuxXilieJiaocheng20201031Fix1/file.epub
MofanPythonGitLinuxXilieJiaocheng20201031Fix1/index.html
MofanPythonGitLinuxXilieJiaocheng20201031Fix1/css/__init__.py
MofanPythonGitLinuxXilieJiaocheng20201031Fix1/css/annotations.css
MofanPythonGitLinuxXilieJiaocheng20201031Fix1/css/main.css
MofanPythonGitLinuxXilieJiaocheng20201031Fix1/css/normalize.css
MofanPythonGitLinuxXilieJiaocheng20201031Fix1/css/popup.css
MofanPythonGitLinuxXilieJiaocheng20201031Fix1/font/__init__.py
MofanPythonGitLinuxXilieJiaocheng20201031Fix1/font/fontello.eot
MofanPythonGitLinuxXilieJiaocheng20201031Fix1/font/fontello.svg
MofanPythonGitLinuxXilieJiaocheng20201031Fix1/font/fontello.ttf
MofanPythonGitLinuxXilieJiaocheng20201031Fix1/font/fontello.woff
MofanPythonGitLinuxXilieJiaocheng20201031Fix1/img/__init__.py
MofanPythonGitLinuxXilieJiaocheng20201031Fix1/img/annotator-glyph-sprite.png
MofanPythonGitLinuxXilieJiaocheng20201031Fix1/img/annotator-icon-sprite.png
MofanPythonGitLinuxXilieJiaocheng20201031Fix1/img/apple-touch-icon.png
MofanPythonGitLinuxXilieJiaocheng20201031Fix1/img/cancelfullscreen.png
MofanPythonGitLinuxXilieJiaocheng20201031Fix1/img/close.png
MofanPythonGitLinuxXilieJiaocheng20201031Fix1/img/fullscreen.png
MofanPythonGitLinuxXilieJiaocheng20201031Fix1/img/loader.gif
MofanPythonGitLinuxXilieJiaocheng20201031Fix1/img/menu-icon.png
MofanPythonGitLinuxXilieJiaocheng20201031Fix1/img/save.png
MofanPythonGitLinuxXilieJiaocheng20201031Fix1/img/saved.png
MofanPythonGitLinuxXilieJiaocheng20201031Fix1/img/settings-s.png
MofanPythonGitLinuxXilieJiaocheng20201031Fix1/img/settings.png
MofanPythonGitLinuxXilieJiaocheng20201031Fix1/img/star.png
MofanPythonGitLinuxXilieJiaocheng20201031Fix1/js/__init__.py
MofanPythonGitLinuxXilieJiaocheng20201031Fix1/js/epub.js
mofan_python_git_linux_xilie_jiaocheng_2020_10_31_fix1-2025.3.24.0.dist-info/METADATA
mofan_python_git_linux_xilie_jiaocheng_2020_10_31_fix1-2025.3.24.0.dist-info/WHEEL
mofan_python_git_linux_xilie_jiaocheng_2020_10_31_fix1-2025.3.24.0.dist-info/entry_points.txt
mofan_python_git_linux_xilie_jiaocheng_2020_10_31_fix1-2025.3.24.0.dist-info/top_level.txt
mofan_python_git_linux_xilie_jiaocheng_2020_10_31_fix1-2025.3.24.0.dist-info/RECORD
